pygame_fpak/__init__.py
pygame_fpak/__main__.py
pygame_fpak/inner.py
pygame_fpak/main.py
pygame_fpak-0.1.dist-info/WHEEL
pygame_fpak-0.1.dist-info/METADATA
pygame_fpak-0.1.dist-info/RECORD
