Metadata-Version: 1.2
Name: pygame_fpak
Version: 0.1
Summary: Flatpak packaging for pygame games.
Home-page: https://github.com/takluyver/pygame-flatpak-test
License: UNKNOWN
Author: Thomas Kluyver
Author-email: thomas@kluyver.me.uk
Requires-Python: >=3.5
Classifier: License :: OSI Approved :: MIT License
Requires-Dist: pytoml
